collective.fingerpointing-1.8.3-py2.7-nspkg.pth
collective/fingerpointing/__init__.py
collective/fingerpointing/config.py
collective/fingerpointing/configure.zcml
collective/fingerpointing/controlpanel.py
collective/fingerpointing/interfaces.py
collective/fingerpointing/logger.py
collective/fingerpointing/profiles.zcml
collective/fingerpointing/setuphandlers.py
collective/fingerpointing/testing.py
collective/fingerpointing/utils.py
collective/fingerpointing/Extensions/Install.py
collective/fingerpointing/Extensions/__init__.py
collective/fingerpointing/browser/__init__.py
collective/fingerpointing/browser/configure.zcml
collective/fingerpointing/browser/logview.pt
collective/fingerpointing/browser/logview.py
collective/fingerpointing/browser/static/fingerpointing-icon.png
collective/fingerpointing/locales/collective.fingerpointing.pot
collective/fingerpointing/locales/manual.pot
collective/fingerpointing/locales/plone.pot
collective/fingerpointing/locales/de/LC_MESSAGES/collective.fingerpointing.mo
collective/fingerpointing/locales/de/LC_MESSAGES/collective.fingerpointing.po
collective/fingerpointing/locales/de/LC_MESSAGES/plone.mo
collective/fingerpointing/locales/de/LC_MESSAGES/plone.po
collective/fingerpointing/locales/es/LC_MESSAGES/collective.fingerpointing.mo
collective/fingerpointing/locales/es/LC_MESSAGES/collective.fingerpointing.po
collective/fingerpointing/locales/es/LC_MESSAGES/plone.mo
collective/fingerpointing/locales/es/LC_MESSAGES/plone.po
collective/fingerpointing/locales/fr/LC_MESSAGES/collective.fingerpointing.mo
collective/fingerpointing/locales/fr/LC_MESSAGES/collective.fingerpointing.po
collective/fingerpointing/locales/fr/LC_MESSAGES/plone.mo
collective/fingerpointing/locales/fr/LC_MESSAGES/plone.po
collective/fingerpointing/locales/pt_BR/LC_MESSAGES/collective.fingerpointing.mo
collective/fingerpointing/locales/pt_BR/LC_MESSAGES/collective.fingerpointing.po
collective/fingerpointing/locales/pt_BR/LC_MESSAGES/plone.mo
collective.fingerpointing-1.8.3.dist-info/METADATA
collective.fingerpointing-1.8.3.dist-info/WHEEL
collective.fingerpointing-1.8.3.dist-info/entry_points.txt
collective.fingerpointing-1.8.3.dist-info/namespace_packages.txt
collective.fingerpointing-1.8.3.dist-info/top_level.txt
collective.fingerpointing-1.8.3.dist-info/RECORD
