Metadata-Version: 2.1
Name: collective.fingerpointing
Version: 1.8.3
Summary: Keep track of different events and write them down to an audit log.
Home-page: https://github.com/collective/collective.fingerpointing
Author: Hector Velarde
Author-email: hector.velarde@gmail.com
License: UNKNOWN
Keywords: plone events subscribers log audit security
Platform: UNKNOWN
Classifier: Development Status :: 5 - Production/Stable
Classifier: Environment :: Web Environment
Classifier: Framework :: Plone :: 4.3
Classifier: Framework :: Plone :: 5.1
Classifier: Framework :: Plone :: 5.2
Classifier: Framework :: Plone :: 6.0
Classifier: Framework :: Plone :: Addon
Classifier: Framework :: Plone
Classifier: Intended Audience :: System Administrators
Classifier: License :: OSI Approved :: GNU General Public License v2 (GPLv2)
Classifier: Operating System :: OS Independent
Classifier: Programming Language :: Python :: 2.7
Classifier: Programming Language :: Python :: 3.6
Classifier: Programming Language :: Python :: 3.7
Classifier: Programming Language :: Python :: 3.8
Classifier: Programming Language :: Python :: 3.9
Classifier: Programming Language :: Python
Classifier: Topic :: Software Development :: Libraries :: Python Modules
Classifier: Topic :: System :: Logging
Requires-Dist: file-read-backwards
Requires-Dist: plone.api (>=1.5.1)
Requires-Dist: plone.app.registry
Requires-Dist: plone.registry
Requires-Dist: Products.CMFCore
Requires-Dist: Products.CMFPlone (>=4.3)
Requires-Dist: Products.GenericSetup
Requires-Dist: Products.PlonePAS (>=5.0.9)
Requires-Dist: Products.PluggableAuthService (>=1.11.0)
Requires-Dist: setuptools
Requires-Dist: six
Requires-Dist: zc.lockfile (>=1.2.1)
Requires-Dist: zope.component
Requires-Dist: zope.globalrequest
Requires-Dist: zope.i18nmessageid
Requires-Dist: zope.interface
Requires-Dist: zope.lifecycleevent
Requires-Dist: zope.schema
Provides-Extra: test
Requires-Dist: AccessControl ; extra == 'test'
Requires-Dist: plone.app.dexterity ; extra == 'test'
Requires-Dist: plone.app.iterate ; extra == 'test'
Requires-Dist: plone.app.testing ; extra == 'test'
Requires-Dist: plone.browserlayer ; extra == 'test'
Requires-Dist: plone.testing ; extra == 'test'
Requires-Dist: testfixtures ; extra == 'test'
Requires-Dist: zope.component ; extra == 'test'
Requires-Dist: zope.event ; extra == 'test'
